fundamentalvision/__init__.py
fundamentalvision/acoes.py
fundamentalvision/app.py
fundamentalvision/dashboard.py
fundamentalvision/data_handler.py
tests/__init__.py
tests/test_acoes.py
tests/test_app.py
tests/test_dashboard.py
tests/test_data_handler.py
tests/test_fundamentalvision.py
fundamentalvision-0.1.0.dist-info/LICENCE
fundamentalvision-0.1.0.dist-info/METADATA
fundamentalvision-0.1.0.dist-info/WHEEL
fundamentalvision-0.1.0.dist-info/top_level.txt
fundamentalvision-0.1.0.dist-info/RECORD
