Metadata-Version: 2.2
Name: fundamentalvision
Version: 0.1.0
Summary: A package for fundamental analysis of stocks on Brazil B3 Exchange.
Home-page: https://github.com/HeannaReis/fundamentalvision
Author: Joel Ferreira Heanna dos Reis
Author-email: heannareis@gmail.com
Classifier: Programming Language :: Python :: 3
Classifier: License :: OSI Approved :: MIT License
Classifier: Operating System :: OS Independent
Requires-Python: >=3.6
License-File: LICENCE
Requires-Dist: pandas
Requires-Dist: requests
Requires-Dist: beautifulsoup4
Requires-Dist: streamlit
Requires-Dist: plotly
Requires-Dist: fundamentus
Provides-Extra: dev
Requires-Dist: pytest; extra == "dev"
Dynamic: author
Dynamic: author-email
Dynamic: classifier
Dynamic: description
Dynamic: description-content-type
Dynamic: home-page
Dynamic: provides-extra
Dynamic: requires-dist
Dynamic: requires-python
Dynamic: summary
